gperiod/__init__.py
gperiod/f.py
gperiod/g.py
gperiod-0.0.5.dist-info/LICENSE
gperiod-0.0.5.dist-info/METADATA
gperiod-0.0.5.dist-info/WHEEL
gperiod-0.0.5.dist-info/top_level.txt
gperiod-0.0.5.dist-info/RECORD
