Metadata-Version: 2.2
Name: gperiod
Version: 0.0.5
Summary: General datetime period library
Author-email: Dima Burmistrov <pyctrl.dev@gmail.com>
License: Copyright (c) 2023-2025 Dmitry Burmistrov
Project-URL: homepage, https://github.com/pyctrl/gperiod
Project-URL: issues, https://github.com/pyctrl/gperiod/issues
Keywords: period,periods,time interval,datetime,duration
Classifier: Programming Language :: Python :: 3
Classifier: License :: OSI Approved :: MIT License
Classifier: Operating System :: OS Independent
Requires-Python: >=3.8
License-File: LICENSE
